LICENSE.txt
MANIFEST.in
README.md
setup.py
mapdata/mapdata.py
mapdata.egg-info/PKG-INFO
mapdata.egg-info/SOURCES.txt
mapdata.egg-info/dependency_links.txt
mapdata.egg-info/requires.txt
mapdata.egg-info/top_level.txt
mapdata/configfile/mapdata.conf
mapdata/symbols/16x16/0.xbm
mapdata/symbols/16x16/1.xbm
mapdata/symbols/16x16/2.xbm
mapdata/symbols/16x16/3.xbm
mapdata/symbols/16x16/4.xbm
mapdata/symbols/16x16/5.xbm
mapdata/symbols/16x16/6.xbm
mapdata/symbols/16x16/7.xbm
mapdata/symbols/16x16/8.xbm
mapdata/symbols/16x16/9.xbm
mapdata/symbols/16x16/A.xbm
mapdata/symbols/16x16/B.xbm
mapdata/symbols/16x16/C.xbm
mapdata/symbols/16x16/D.xbm
mapdata/symbols/16x16/E.xbm
mapdata/symbols/16x16/F.xbm
mapdata/symbols/16x16/G.xbm
mapdata/symbols/16x16/H.xbm
mapdata/symbols/16x16/I.xbm
mapdata/symbols/16x16/J.xbm
mapdata/symbols/16x16/K.xbm
mapdata/symbols/16x16/L.xbm
mapdata/symbols/16x16/M.xbm
mapdata/symbols/16x16/N.xbm
mapdata/symbols/16x16/O.xbm
mapdata/symbols/16x16/P.xbm
mapdata/symbols/16x16/Q.xbm
mapdata/symbols/16x16/R.xbm
mapdata/symbols/16x16/S.xbm
mapdata/symbols/16x16/T.xbm
mapdata/symbols/16x16/U.xbm
mapdata/symbols/16x16/V.xbm
mapdata/symbols/16x16/W.xbm
mapdata/symbols/16x16/X.xbm
mapdata/symbols/16x16/Y.xbm
mapdata/symbols/16x16/Z.xbm
mapdata/symbols/16x16/airplane.xbm
mapdata/symbols/16x16/anchor.xbm
mapdata/symbols/16x16/ball.xbm
mapdata/symbols/16x16/ball_small.xbm
mapdata/symbols/16x16/bar.xbm
mapdata/symbols/16x16/bars.xbm
mapdata/symbols/16x16/binoculars.xbm
mapdata/symbols/16x16/bird.xbm
mapdata/symbols/16x16/block.xbm
mapdata/symbols/16x16/block_small.xbm
mapdata/symbols/16x16/bookmark.xbm
mapdata/symbols/16x16/box_stack.xbm
mapdata/symbols/16x16/camera.xbm
mapdata/symbols/16x16/cancel.xbm
mapdata/symbols/16x16/car.xbm
mapdata/symbols/16x16/car2.xbm
mapdata/symbols/16x16/center8.xbm
mapdata/symbols/16x16/check.xbm
mapdata/symbols/16x16/check_circle.xbm
mapdata/symbols/16x16/checkbox.xbm
mapdata/symbols/16x16/checkerboard.xbm
mapdata/symbols/16x16/chevrons.xbm
mapdata/symbols/16x16/circle.xbm
mapdata/symbols/16x16/circle_bar.xbm
mapdata/symbols/16x16/circle_plus.xbm
mapdata/symbols/16x16/circle_stipple.xbm
