Metadata-Version: 2.1
Name: mapdata
Version: 3.5.0
Summary: An interactive map and table explorer for geographic coordinates in a spreadsheet, CSV file, or database
Home-page: https://osdn.net/project/mapdata/
Author: Dreas Nielsen
Author-email: cortice@tutanota.com
License: GPL
Keywords: Map,Locations,CRS,CSV,Spreadsheet,Database,PNG,JPG,Postscript
Classifier: Development Status :: 5 - Production/Stable
Classifier: Environment :: Console
Classifier: Environment :: X11 Applications
Classifier: Environment :: Win32 (MS Windows)
Classifier: Intended Audience :: End Users/Desktop
Classifier: Intended Audience :: Information Technology
Classifier: License :: OSI Approved :: GNU General Public License (GPL)
Classifier: Natural Language :: English
Classifier: Operating System :: OS Independent
Classifier: Operating System :: POSIX
Classifier: Operating System :: Microsoft :: Windows
Classifier: Programming Language :: Python :: 3
Classifier: Topic :: Office/Business
Classifier: Topic :: Scientific/Engineering
Requires-Python: >=3.8
License-File: LICENSE.txt
Requires-Dist: tkintermapview
Requires-Dist: pyproj
Requires-Dist: jenkspy
Requires-Dist: odfpy
Requires-Dist: openpyxl
Requires-Dist: xlrd
Requires-Dist: matplotlib
Requires-Dist: seaborn
Requires-Dist: loess
Requires-Dist: statsmodels
Requires-Dist: scipy
Requires-Dist: scikit-learn
Requires-Dist: pymannkendall
Requires-Dist: umap-learn
Requires-Dist: pynndescent
